{
    "name": "ash_exec",
    "description": "Send a message to ash on another host.  This can be a question, information, or instructions.  Keep in mind they have the same features and functions as you.  You can use this to coordinate troubleshooting or other cool ways",
    "parameters": {
        "type": "object",
        "properties": {
            "host": {
                "type": "string",
                "description": "The hostname or IP address of the host to send the message to"
            },
            "message": {
                "type": "string",
                "description": "The message to send to the other ash"
            }
        },
        "required": [
            "host",
            "message"
        ]
    }
}